randrctl/__init__.py
randrctl/__main__.py
randrctl/cli.py
randrctl/context.py
randrctl/ctl.py
randrctl/exception.py
randrctl/model.py
randrctl/profile.py
randrctl/py.typed
randrctl/xrandr.py
randrctl/setup/99-randrctl.rules
randrctl/setup/config.yaml
randrctl-1.11.0.dist-info/METADATA
randrctl-1.11.0.dist-info/WHEEL
randrctl-1.11.0.dist-info/entry_points.txt
randrctl-1.11.0.dist-info/licenses/LICENSE.txt
randrctl-1.11.0.dist-info/RECORD
