Metadata-Version: 2.4
Name: randrctl
Version: 1.11.0
Summary: Profile based screen manager for X
Project-URL: Homepage, https://github.com/koiuo/randrctl
Project-URL: Repository, https://github.com/koiuo/randrctl
Project-URL: Issues, https://github.com/koiuo/randrctl/issues
Author: Dmytro Kostiuchenko
License: GPL-3.0
License-File: LICENSE.txt
Classifier: Development Status :: 4 - Beta
Classifier: Environment :: X11 Applications
Classifier: Intended Audience :: End Users/Desktop
Classifier: License :: OSI Approved :: GNU General Public License v3 (GPLv3)
Classifier: Operating System :: POSIX :: Linux
Classifier: Programming Language :: Python :: 3
Classifier: Programming Language :: Python :: 3.7
Classifier: Programming Language :: Python :: 3.8
Classifier: Programming Language :: Python :: 3.9
Classifier: Programming Language :: Python :: 3.10
Classifier: Programming Language :: Python :: 3.11
Classifier: Programming Language :: Python :: 3.12
Classifier: Topic :: Desktop Environment
Classifier: Topic :: Utilities
Requires-Python: >=3.7
Requires-Dist: argcomplete
Requires-Dist: pyyaml
